[{"input": 31, "text": "Mr.", "boundingBox": [131, 80, 163, 79, 163, 97, 131, 97]}, {"input": 31, "text": "M's", "boundingBox": [168, 78, 199, 77, 199, 96, 168, 97]}, {"input": 31, "text": "Hot", "boundingBox": [205, 77, 238, 75, 238, 95, 206, 96]}, {"input": 31, "text": "Wings", "boundingBox": [243, 75, 294, 73, 295, 94, 244, 95]}, {"input": 31, "text": "&", "boundingBox": [302, 72, 313, 72, 314, 93, 303, 94]}, {"input": 31, "text": "Things", "boundingBox": [321, 72, 379, 69, 380, 91, 322, 93]}, {"input": 31, "text": "Inc", "boundingBox": [388, 68, 415, 67, 416, 90, 389, 91]}, {"input": 31, "text": "886", "boundingBox": [168, 97, 198, 96, 198, 113, 168, 113]}, {"input": 31, "text": "N.", "boundingBox": [216, 95, 238, 95, 238, 114, 216, 114]}, {"input": 31, "text": "Garfield", "boundingBox": [245, 94, 323, 93, 323, 113, 244, 114]}, {"input": 31, "text": "Ave", "boundingBox": [331, 93, 360, 93, 360, 113, 330, 113]}, {"input": 31, "text": "Montebello,", "boundingBox": [167, 115, 278, 114, 278, 134, 167, 134]}, {"input": 31, "text": "CA", "boundingBox": [283, 114, 306, 114, 306, 133, 283, 134]}, {"input": 31, "text": "90640", "boundingBox": [313, 114, 360, 114, 360, 132, 313, 133]}, {"input": 31, "text": "(323)", "boundingBox": [197, 135, 250, 134, 249, 153, 197, 154]}, {"input": 31, "text": "477-1345", "boundingBox": [255, 134, 331, 133, 331, 153, 255, 153]}, {"input": 31, "text": "Server:", "boundingBox": [70, 178, 143, 179, 143, 197, 70, 197]}, {"input": 31, "text": "Jose", "boundingBox": [149, 179, 188, 178, 189, 197, 150, 197]}, {"input": 31, "text": "Station:", "boundingBox": [361, 175, 442, 162, 445, 180, 364, 195]}, {"input": 31, "text": "8", "boundingBox": [446, 161, 456, 159, 460, 177, 449, 179]}, {"input": 31, "text": "Dine", "boundingBox": [224, 219, 267, 220, 267, 239, 224, 240]}, {"input": 31, "text": "In", "boundingBox": [275, 220, 294, 219, 295, 238, 276, 239]}, {"input": 31, "text": "Table:", "boundingBox": [69, 244, 132, 244, 132, 263, 68, 263]}, {"input": 31, "text": "1", "boundingBox": [139, 244, 147, 244, 147, 262, 138, 262]}, {"input": 31, "text": "Guests", "boundingBox": [370, 241, 427, 230, 431, 248, 374, 258]}, {"input": 31, "text": ":", "boundingBox": [431, 230, 442, 228, 445, 245, 434, 247]}, {"input": 31, "text": "1", "boundingBox": [451, 226, 457, 225, 461, 241, 454, 243]}, {"input": 31, "text": "10.00", "boundingBox": [413, 275, 460, 266, 464, 285, 416, 293]}, {"input": 31, "text": "1", "boundingBox": [66, 287, 80, 287, 80, 309, 66, 308]}, {"input": 31, "text": "Ribeye", "boundingBox": [84, 287, 149, 287, 149, 309, 84, 309]}, {"input": 31, "text": "Steak", "boundingBox": [155, 287, 208, 286, 208, 308, 155, 309]}, {"input": 31, "text": "Lunch", "boundingBox": [214, 286, 267, 286, 267, 307, 214, 308]}, {"input": 31, "text": "10", "boundingBox": [277, 286, 295, 285, 296, 307, 277, 307]}, {"input": 31, "text": ">", "boundingBox": [86, 312, 99, 312, 98, 330, 85, 330]}, {"input": 31, "text": "med-rare", "boundingBox": [103, 312, 185, 314, 184, 332, 103, 330]}, {"input": 31, "text": "10.00", "boundingBox": [415, 343, 464, 335, 467, 355, 418, 362]}, {"input": 31, "text": "SUB", "boundingBox": [64, 356, 95, 357, 94, 375, 63, 375]}, {"input": 31, "text": "TOTAL", "boundingBox": [106, 357, 153, 358, 153, 376, 105, 375]}, {"input": 31, "text": ":", "boundingBox": [157, 358, 163, 358, 162, 376, 156, 376]}, {"input": 31, "text": "Tax", "boundingBox": [64, 379, 91, 379, 91, 398, 63, 398]}, {"input": 31, "text": ":", "boundingBox": [95, 379, 99, 379, 99, 398, 95, 398]}, {"input": 31, "text": "0.", "boundingBox": [424, 365, 441, 363, 444, 382, 426, 385]}, {"input": 31, "text": "95", "boundingBox": [445, 362, 465, 360, 467, 379, 448, 382]}, {"input": 31, "text": "TOTAL:", "boundingBox": [61, 426, 119, 426, 119, 462, 61, 462]}, {"input": 31, "text": "$10.95", "boundingBox": [404, 414, 466, 408, 470, 446, 408, 453]}, {"input": 31, "text": ">>", "boundingBox": [171, 485, 194, 485, 195, 522, 171, 521]}, {"input": 31, "text": "Ticket", "boundingBox": [202, 485, 266, 484, 266, 523, 202, 522]}, {"input": 31, "text": "#:", "boundingBox": [273, 484, 299, 484, 300, 523, 273, 523]}, {"input": 31, "text": "32", "boundingBox": [307, 484, 331, 484, 330, 523, 307, 523]}, {"input": 31, "text": "<<", "boundingBox": [338, 484, 362, 484, 361, 523, 338, 523]}, {"input": 31, "text": "6/28/2019", "boundingBox": [159, 523, 257, 522, 257, 545, 159, 546]}, {"input": 31, "text": "2:16:34", "boundingBox": [265, 522, 342, 521, 342, 544, 264, 545]}, {"input": 31, "text": "PM", "boundingBox": [347, 521, 370, 521, 370, 544, 346, 544]}, {"input": 31, "text": "10%", "boundingBox": [55, 574, 88, 573, 88, 596, 55, 596]}, {"input": 31, "text": "Gratuity", "boundingBox": [96, 573, 184, 573, 183, 595, 95, 596]}, {"input": 31, "text": "=", "boundingBox": [191, 573, 205, 572, 204, 594, 190, 595]}, {"input": 31, "text": "$1.00", "boundingBox": [211, 572, 263, 572, 262, 593, 210, 594]}, {"input": 31, "text": "15%", "boundingBox": [54, 599, 88, 599, 87, 621, 54, 621]}, {"input": 31, "text": "Gratuity", "boundingBox": [95, 599, 183, 598, 183, 620, 94, 621]}, {"input": 31, "text": "=", "boundingBox": [190, 598, 204, 598, 204, 620, 190, 620]}, {"input": 31, "text": "$1.50", "boundingBox": [211, 598, 265, 597, 265, 618, 211, 620]}, {"input": 31, "text": "20%", "boundingBox": [52, 623, 87, 624, 87, 646, 52, 646]}, {"input": 31, "text": "Gratuity", "boundingBox": [93, 624, 182, 623, 182, 645, 93, 646]}, {"input": 31, "text": "=", "boundingBox": [189, 623, 204, 623, 203, 645, 189, 645]}, {"input": 31, "text": "$2.00", "boundingBox": [211, 623, 264, 622, 263, 644, 211, 645]}]