[{"input": 29, "text": "CASA", "boundingBox": [241, 217, 281, 218, 281, 231, 241, 230]}, {"input": 29, "text": "CHAN", "boundingBox": [288, 219, 329, 220, 328, 232, 288, 231]}, {"input": 29, "text": "RESTAURANT", "boundingBox": [335, 220, 437, 221, 436, 234, 335, 232]}, {"input": 29, "text": "445", "boundingBox": [300, 231, 321, 232, 321, 243, 300, 242]}, {"input": 29, "text": "Palm", "boundingBox": [324, 232, 350, 233, 350, 244, 324, 243]}, {"input": 29, "text": "Ave", "boundingBox": [359, 233, 379, 233, 380, 244, 359, 244]}, {"input": 29, "text": "Hialeah,", "boundingBox": [286, 241, 335, 243, 335, 254, 286, 252]}, {"input": 29, "text": "FL", "boundingBox": [337, 243, 351, 243, 351, 254, 337, 254]}, {"input": 29, "text": "33010", "boundingBox": [356, 243, 392, 243, 392, 254, 355, 254]}, {"input": 29, "text": "(305)", "boundingBox": [293, 253, 327, 253, 326, 265, 293, 264]}, {"input": 29, "text": "640-8828", "boundingBox": [329, 253, 387, 254, 387, 265, 328, 265]}, {"input": 29, "text": "Find", "boundingBox": [201, 274, 228, 275, 228, 287, 201, 287]}, {"input": 29, "text": "us", "boundingBox": [231, 275, 246, 275, 246, 287, 230, 287]}, {"input": 29, "text": "on", "boundingBox": [249, 275, 264, 276, 264, 287, 249, 287]}, {"input": 29, "text": "instagram", "boundingBox": [267, 276, 326, 278, 325, 290, 267, 288]}, {"input": 29, "text": "@casa_chan_restaurant", "boundingBox": [202, 287, 351, 290, 351, 302, 202, 299]}, {"input": 29, "text": "Facebook", "boundingBox": [355, 290, 415, 290, 415, 303, 355, 302]}, {"input": 29, "text": "Casa", "boundingBox": [419, 290, 450, 291, 450, 304, 418, 303]}, {"input": 29, "text": "Chan", "boundingBox": [200, 299, 232, 300, 231, 312, 200, 311]}, {"input": 29, "text": "Restaurant", "boundingBox": [235, 300, 304, 302, 304, 313, 234, 312]}, {"input": 29, "text": "ORDER:", "boundingBox": [296, 316, 374, 316, 374, 333, 295, 332]}, {"input": 29, "text": "9", "boundingBox": [377, 316, 387, 316, 387, 333, 377, 333]}, {"input": 29, "text": "Dine", "boundingBox": [307, 337, 351, 338, 351, 354, 307, 354]}, {"input": 29, "text": "In", "boundingBox": [356, 338, 374, 338, 373, 355, 355, 354]}, {"input": 29, "text": "Cashier:", "boundingBox": [195, 354, 249, 355, 249, 369, 195, 368]}, {"input": 29, "text": "Diana", "boundingBox": [252, 355, 290, 356, 290, 370, 251, 369]}, {"input": 29, "text": "Z", "boundingBox": [293, 356, 301, 356, 300, 370, 292, 370]}, {"input": 29, "text": "21-Dec-2014", "boundingBox": [195, 368, 282, 369, 282, 383, 195, 382]}, {"input": 29, "text": "5:23:42P", "boundingBox": [285, 369, 341, 370, 341, 384, 285, 383]}, {"input": 29, "text": "1", "boundingBox": [194, 409, 201, 411, 198, 423, 191, 422]}, {"input": 29, "text": "#12", "boundingBox": [217, 412, 243, 413, 243, 426, 217, 425]}, {"input": 29, "text": "Wonton", "boundingBox": [246, 413, 295, 413, 295, 427, 246, 426]}, {"input": 29, "text": "or", "boundingBox": [299, 413, 314, 414, 314, 428, 299, 427]}, {"input": 29, "text": "Egg", "boundingBox": [316, 414, 341, 414, 341, 428, 316, 428]}, {"input": 29, "text": "Drop", "boundingBox": [345, 414, 375, 414, 375, 429, 345, 428]}, {"input": 29, "text": "or", "boundingBox": [379, 413, 393, 413, 392, 429, 379, 429]}, {"input": 29, "text": "$3,75", "boundingBox": [456, 414, 495, 415, 495, 427, 456, 427]}, {"input": 29, "text": "Mixed", "boundingBox": [216, 427, 256, 428, 256, 441, 216, 440]}, {"input": 29, "text": "Dinner", "boundingBox": [260, 428, 303, 429, 302, 442, 259, 441]}, {"input": 29, "text": "Wonton", "boundingBox": [364, 442, 416, 443, 416, 458, 364, 457]}, {"input": 29, "text": "Soup", "boundingBox": [420, 443, 456, 444, 456, 458, 420, 458]}, {"input": 29, "text": "$0.00", "boundingBox": [459, 444, 499, 443, 500, 458, 459, 458]}, {"input": 29, "text": "#01", "boundingBox": [213, 472, 241, 472, 241, 487, 213, 486]}, {"input": 29, "text": "Egg", "boundingBox": [244, 472, 271, 472, 270, 487, 243, 487]}, {"input": 29, "text": "Roll", "boundingBox": [274, 472, 301, 472, 300, 487, 273, 487]}, {"input": 29, "text": "$3.00", "boundingBox": [462, 474, 501, 473, 501, 487, 462, 488]}, {"input": 29, "text": "#23", "boundingBox": [212, 487, 241, 488, 241, 502, 213, 501]}, {"input": 29, "text": "Juice", "boundingBox": [245, 488, 282, 488, 282, 503, 245, 502]}, {"input": 29, "text": "Chinesse", "boundingBox": [285, 488, 350, 489, 350, 504, 285, 503]}, {"input": 29, "text": "Chop", "boundingBox": [352, 489, 388, 490, 388, 505, 352, 504]}, {"input": 29, "text": "$8.99", "boundingBox": [464, 490, 504, 490, 504, 503, 464, 504]}, {"input": 29, "text": "Suey", "boundingBox": [212, 503, 246, 504, 245, 518, 211, 518]}, {"input": 29, "text": "Honduran", "boundingBox": [249, 504, 319, 505, 318, 520, 248, 518]}, {"input": 29, "text": "Style", "boundingBox": [323, 505, 358, 506, 358, 520, 323, 520]}, {"input": 29, "text": "Dinner", "boundingBox": [210, 520, 258, 521, 257, 534, 210, 534]}, {"input": 29, "text": "1", "boundingBox": [183, 536, 190, 537, 188, 549, 182, 548]}, {"input": 29, "text": "Tropical", "boundingBox": [211, 535, 269, 536, 269, 550, 211, 550]}, {"input": 29, "text": "$5.00", "boundingBox": [469, 538, 511, 537, 511, 552, 469, 552]}, {"input": 29, "text": "2", "boundingBox": [208, 552, 218, 552, 218, 568, 208, 568]}, {"input": 29, "text": "@", "boundingBox": [223, 552, 235, 552, 234, 568, 223, 568]}, {"input": 29, "text": "$2.50/12", "boundingBox": [241, 552, 308, 553, 308, 568, 241, 568]}, {"input": 29, "text": "oz", "boundingBox": [311, 553, 328, 553, 328, 568, 311, 568]}, {"input": 29, "text": "1", "boundingBox": [180, 568, 187, 569, 185, 583, 178, 581]}, {"input": 29, "text": "Tamal", "boundingBox": [208, 569, 252, 569, 252, 584, 207, 584]}, {"input": 29, "text": "De", "boundingBox": [255, 569, 276, 569, 276, 585, 255, 584]}, {"input": 29, "text": "Pollo", "boundingBox": [279, 569, 315, 569, 315, 585, 279, 585]}, {"input": 29, "text": "$3.50", "boundingBox": [473, 571, 517, 571, 517, 586, 473, 587]}, {"input": 29, "text": "1", "boundingBox": [206, 585, 217, 585, 217, 602, 206, 602]}, {"input": 29, "text": "@", "boundingBox": [221, 585, 233, 585, 233, 602, 220, 602]}, {"input": 29, "text": "$3.50/each", "boundingBox": [238, 586, 322, 587, 322, 603, 238, 602]}, {"input": 29, "text": "Subtotal", "boundingBox": [172, 621, 239, 622, 238, 639, 172, 638]}, {"input": 29, "text": "$24.24", "boundingBox": [468, 625, 523, 625, 524, 641, 468, 641]}, {"input": 29, "text": "Tax", "boundingBox": [173, 641, 196, 641, 196, 656, 173, 656]}, {"input": 29, "text": "$1.70", "boundingBox": [480, 644, 526, 645, 526, 661, 480, 660]}, {"input": 29, "text": "Total", "boundingBox": [169, 678, 206, 679, 206, 695, 169, 694]}, {"input": 29, "text": "$25.94", "boundingBox": [474, 682, 533, 683, 533, 701, 474, 700]}, {"input": 29, "text": "Order", "boundingBox": [163, 720, 208, 721, 208, 739, 163, 738]}, {"input": 29, "text": "DMHGRRF9JPM70", "boundingBox": [212, 721, 368, 722, 367, 740, 212, 739]}, {"input": 29, "text": "Bring", "boundingBox": [159, 763, 203, 764, 202, 785, 158, 784]}, {"input": 29, "text": "back", "boundingBox": [207, 764, 247, 764, 246, 786, 206, 785]}, {"input": 29, "text": "this", "boundingBox": [251, 764, 284, 765, 284, 787, 251, 786]}, {"input": 29, "text": "receipt", "boundingBox": [289, 765, 345, 766, 344, 788, 288, 787]}, {"input": 29, "text": "for", "boundingBox": [349, 766, 375, 766, 374, 788, 348, 788]}, {"input": 29, "text": "10%", "boundingBox": [380, 767, 414, 767, 413, 789, 379, 789]}, {"input": 29, "text": "off", "boundingBox": [418, 767, 440, 768, 439, 790, 417, 789]}, {"input": 29, "text": "your", "boundingBox": [444, 768, 482, 769, 480, 791, 443, 790]}, {"input": 29, "text": "next", "boundingBox": [486, 769, 523, 770, 522, 791, 485, 791]}, {"input": 29, "text": "visit!", "boundingBox": [156, 786, 203, 787, 203, 807, 155, 806]}, {"input": 29, "text": ":)", "boundingBox": [207, 788, 219, 788, 219, 807, 207, 807]}, {"input": 29, "text": "Online:", "boundingBox": [226, 833, 285, 835, 284, 856, 226, 855]}, {"input": 29, "text": "https://clover.com/r/", "boundingBox": [289, 835, 477, 838, 476, 859, 289, 856]}, {"input": 29, "text": "DMHGRRF9JPM70", "boundingBox": [267, 860, 437, 861, 436, 882, 267, 880]}]