[
  {
    "input": 34,
    "text": "1660 India Street",
    "label": 0,
    "boundingBox": [
      244,
      71,
      480,
      57,
      482,
      89,
      246,
      103
    ]
  },
  {
    "input": 34,
    "text": "Server: Jake",
    "boundingBox": [
      84,
      154,
      247,
      143,
      249,
      172,
      86,
      182
    ]
  },
  {
    "input": 34,
    "text": "12/17/2017",
    "boundingBox": [
      525,
      127,
      667,
      121,
      668,
      151,
      526,
      157
    ]
  },
  {
    "input": 34,
    "text": "Table 24/1",
    "boundingBox": [
      86,
      184,
      217,
      177,
      219,
      210,
      88,
      217
    ]
  },
  {
    "input": 34,
    "text": "6:29 PM",
    "boundingBox": [
      564,
      161,
      670,
      157,
      671,
      186,
      565,
      190
    ]
  },
  {
    "input": 34,
    "text": "Guests: 2",
    "boundingBox": [
      87,
      220,
      210,
      214,
      211,
      241,
      88,
      247
    ]
  },
  {
    "input": 34,
    "text": "20018",
    "boundingBox": [
      594,
      195,
      667,
      193,
      667,
      219,
      594,
      221
    ]
  },
  {
    "input": 34,
    "text": "G1 Karma Cab Sauv",
    "label": 3,
    "boundingBox": [
      85,
      284,
      316,
      273,
      318,
      303,
      86,
      314
    ]
  },
  {
    "input": 34,
    "text": "12.00",
    "label": 4,
    "boundingBox": [
      600,
      264,
      671,
      261,
      672,
      286,
      601,
      290
    ]
  },
  {
    "input": 34,
    "text": "G1 Douglass Green SB",
    "label": 3,
    "boundingBox": [
      84,
      318,
      359,
      304,
      360,
      333,
      86,
      347
    ]
  },
  {
    "input": 34,
    "text": "11.00",
    "label": 4,
    "boundingBox": [
      603,
      298,
      675,
      294,
      675,
      320,
      604,
      323
    ]
  },
  {
    "input": 34,
    "text": "PKLI Green Curry Scallops",
    "label": 3,
    "boundingBox": [
      82,
      348,
      430,
      336,
      431,
      367,
      83,
      378
    ]
  },
  {
    "input": 34,
    "text": "27.95",
    "label": 4,
    "boundingBox": [
      599,
      329,
      680,
      327,
      680,
      357,
      599,
      359
    ]
  },
  {
    "input": 34,
    "text": "PKLI Piri Piri Chicken",
    "label": 3,
    "boundingBox": [
      81,
      381,
      387,
      373,
      388,
      402,
      81,
      410
    ]
  },
  {
    "input": 34,
    "text": "23. 75",
    "label": 4,
    "boundingBox": [
      605,
      364,
      679,
      363,
      679,
      391,
      606,
      393
    ]
  },
  {
    "input": 34,
    "text": "Subtotal",
    "label": 3,
    "boundingBox": [
      77,
      448,
      190,
      447,
      190,
      475,
      78,
      477
    ]
  },
  {
    "input": 34,
    "text": "74.70",
    "label": 4,
    "boundingBox": [
      605,
      436,
      683,
      435,
      683,
      463,
      605,
      463
    ]
  },
  {
    "input": 34,
    "text": "Tax",
    "label": 3,
    "boundingBox": [
      78,
      484,
      123,
      484,
      123,
      515,
      77,
      514
    ]
  },
  {
    "input": 34,
    "text": "6.00",
    "label": 4,
    "boundingBox": [
      623,
      473,
      682,
      471,
      683,
      499,
      623,
      501
    ]
  },
  {
    "input": 34,
    "text": "Surcharge 3.75% SC*",
    "label": 3,
    "boundingBox": [
      76,
      551,
      346,
      548,
      346,
      579,
      76,
      583
    ]
  },
  {
    "input": 34,
    "text": "2.80",
    "label": 4,
    "boundingBox": [
      625,
      546,
      688,
      545,
      689,
      573,
      626,
      574
    ]
  },
  {
    "input": 34,
    "text": "Total",
    "label": 3,
    "boundingBox": [
      74,
      623,
      144,
      623,
      144,
      652,
      74,
      651
    ]
  },
  {
    "input": 34,
    "text": "83.50",
    "label": 4,
    "boundingBox": [
      614,
      620,
      694,
      619,
      694,
      649,
      614,
      650
    ]
  },
  {
    "input": 34,
    "text": "Balance Due",
    "label": 3,
    "boundingBox": [
      74,
      692,
      393,
      696,
      393,
      729,
      73,
      725
    ]
  },
  {
    "input": 34,
    "text": "83 . 50",
    "label": 4,
    "boundingBox": [
      539,
      694,
      692,
      692,
      693,
      725,
      540,
      727
    ]
  },
  {
    "input": 34,
    "text": "*3. 75% SC - In support",
    "boundingBox": [
      211,
      766,
      546,
      770,
      545,
      806,
      211,
      802
    ]
  },
  {
    "input": 34,
    "text": "of the increases to min wage",
    "boundingBox": [
      167,
      807,
      593,
      812,
      592,
      844,
      167,
      839
    ]
  },
  {
    "input": 34,
    "text": "To find out why, visit",
    "boundingBox": [
      211,
      844,
      548,
      848,
      548,
      884,
      210,
      880
    ]
  },
  {
    "input": 34,
    "text": "www. wn lhosp.com/rttd",
    "boundingBox": [
      224,
      882,
      531,
      886,
      531,
      922,
      223,
      918
    ]
  }
]